[
    {
        "position": 1,
        "imageUrl": "img/1.jpg",
        "name": "JQuery Introduction",
        "link": "JQuery_introduction"
    },
    {
        "position": 2,
        "imageUrl": "img/2.jpg",
        "name": "JQuery Styles",
        "link": "JQuery_styles"
    },
    {
        "position": 3,
        "imageUrl": "img/3.jpg",
        "name": "JQuery More",
        "link": "JQuery_more"
    },
    {
        "position": 4,
        "imageUrl": "img/1.jpg",
        "name": "JQuery More1",
        "link": "JQuery_more1"
    },
    {
        "position": 5,
        "imageUrl": "img/2.jpg",
        "name": "JQuery More2",
        "link": "JQuery_more2"
    },
    {
        "position": 6,
        "imageUrl": "img/3.jpg",
        "name": "JQuery More3",
        "link": "JQuery_more3"
    }
]
